ganita/__init__.py
ganita/lilavati/__init__.py
ganita/lilavati/squares.py
ganita-0.1.0.dist-info/METADATA
ganita-0.1.0.dist-info/WHEEL
ganita-0.1.0.dist-info/licenses/LICENSE
ganita-0.1.0.dist-info/RECORD
