Metadata-Version: 2.3
Name: ganita
Version: 0.1.0
Summary: A package for mathematical calculations using Indian Knowledge System including Lilavati's methods
Project-URL: Homepage, https://github.com/anaadiai/ganita
Project-URL: Bug Tracker, https://github.com/anaadiai/ganita/issues
Author-email: Anaadi Rural AI Center <venkat@anaadi.org>
License-File: LICENSE
Classifier: License :: OSI Approved :: MIT License
Classifier: Operating System :: OS Independent
Classifier: Programming Language :: Python :: 3
Requires-Python: >=3.7
